setup.py
dronekit_solo/__init__.py
dronekit_solo.egg-info/PKG-INFO
dronekit_solo.egg-info/SOURCES.txt
dronekit_solo.egg-info/dependency_links.txt
dronekit_solo.egg-info/pbr.json
dronekit_solo.egg-info/top_level.txt