Metadata-Version: 1.0
Name: dronekit-solo
Version: 1.3.0
Summary: DroneKit methods for Solo-specific features.
Home-page: https://github.com/dronekit/dronekit-solo/
Author: Tim Ryan
Author-email: tim@3drobotics.com
License: UNKNOWN
Platform: UNKNOWN
